{
  "company": {
    "ticker": "META",
    "name": "Meta Platforms Inc.",
    "category": [
      "Mag7",
      "Tech"
    ],
    "cik": "0001326801"
  },
  "reports": [
    {
      "filing": {
        "accessionNumber": "0001628280-25-047240",
        "filingDate": "2025-10-30",
        "reportDate": "2025-09-30",
        "form": "10-Q",
        "url": "https://www.sec.gov/Archives/edgar/data/1326801/000162828025047240/meta-20250930.htm"
      },
      "insights": {
        "guidanceTone": "cautious",
        "guidanceDirection": "not_provided",
        "bookingsGrowth": null,
        "pricingPower": "strong",
        "headcountTrend": "expanding",
        "revenue": 51242,
        "netIncome": 2709,
        "operatingCashFlow": 79586,
        "freeCashFlow": null,
        "daysalesOutstanding": null,
        "deferredRevenue": 924,
        "marketShareMention": null,
        "customerConcentration": null,
        "geographicBreakdown": {
          "United States and Canada": 38.5,
          "Europe": 22.6,
          "Asia-Pacific": 27.9,
          "Rest of World": 11
        },
        "capexAmount": 48308,
        "capexGrowth": 111.6,
        "partnerships": [],
        "supplyChainStatus": "normal",
        "regulatoryHeadwinds": [
          "Privacy litigation",
          "FTC settlements",
          "Attorney General inquiries"
        ],
        "aiInvestmentMentioned": false,
        "priorGuidanceHit": null,
        "managementTone": "defensive",
        "overallSentiment": "neutral",
        "summary": "Meta reported quarterly revenue of $51.2 billion with net income of $2.7 billion, reflecting significant infrastructure investments and ongoing regulatory challenges. The company continues to expand infrastructure spending while managing legal and privacy-related risks.",
        "keyQuotes": []
      },
      "quarter": "Q3 2025",
      "quarterInfo": {
        "calendarQuarter": 3,
        "calendarYear": 2025,
        "fiscalQuarter": 3,
        "fiscalYear": 2025,
        "quarter": "Q3 2025",
        "reportDate": "2025-09-30"
      },
      "analyzedSuccessfully": true
    },
    {
      "filing": {
        "accessionNumber": "0001628280-25-036791",
        "filingDate": "2025-07-31",
        "reportDate": "2025-06-30",
        "form": "10-Q",
        "url": "https://www.sec.gov/Archives/edgar/data/1326801/000162828025036791/meta-20250630.htm"
      },
      "insights": {
        "guidanceTone": "positive",
        "guidanceDirection": "maintained",
        "bookingsGrowth": null,
        "pricingPower": "strong",
        "headcountTrend": "stable",
        "revenue": 47516,
        "netIncome": 18337,
        "operatingCashFlow": 49587,
        "freeCashFlow": null,
        "daysalesOutstanding": null,
        "deferredRevenue": 876,
        "marketShareMention": null,
        "customerConcentration": null,
        "geographicBreakdown": {
          "US_Canada": 38.8,
          "Europe": 23.4,
          "Asia_Pacific": 27.1,
          "Rest_of_World": 10.7
        },
        "capexAmount": 29479,
        "capexGrowth": 102.2,
        "partnerships": [],
        "supplyChainStatus": "normal",
        "regulatoryHeadwinds": [
          "FTC consent order modifications",
          "Privacy litigation"
        ],
        "aiInvestmentMentioned": false,
        "priorGuidanceHit": null,
        "managementTone": "confident",
        "overallSentiment": "bullish",
        "summary": "Meta delivered strong quarterly performance with robust revenue growth and substantial net income. The company continues to invest heavily in infrastructure while maintaining stable operations amid ongoing regulatory challenges.",
        "keyQuotes": []
      },
      "quarter": "Q2 2025",
      "quarterInfo": {
        "calendarQuarter": 2,
        "calendarYear": 2025,
        "fiscalQuarter": 2,
        "fiscalYear": 2025,
        "quarter": "Q2 2025",
        "reportDate": "2025-06-30"
      },
      "analyzedSuccessfully": true
    },
    {
      "filing": {
        "accessionNumber": "0001326801-25-000054",
        "filingDate": "2025-05-01",
        "reportDate": "2025-03-31",
        "form": "10-Q",
        "url": "https://www.sec.gov/Archives/edgar/data/1326801/000132680125000054/meta-20250331.htm"
      },
      "insights": {
        "revenue": 42314,
        "netIncome": 16644,
        "guidanceTone": "positive",
        "guidanceDirection": "maintained",
        "pricingPower": "strong",
        "headcountTrend": "expanding",
        "operatingCashFlow": 24026,
        "freeCashFlow": null,
        "daysalesOutstanding": null,
        "deferredRevenue": 778,
        "marketShareMention": null,
        "customerConcentration": null,
        "geographicBreakdown": {
          "unitedStatesAndCanada": 39.9,
          "europe": 22.7,
          "asiaPacific": 26.6,
          "restOfWorld": 10.8
        },
        "capexAmount": 12941,
        "capexGrowth": 102.2,
        "partnerships": [],
        "supplyChainStatus": "normal",
        "regulatoryHeadwinds": [
          "FTC consent order modifications",
          "GDPR compliance investigations",
          "Privacy lawsuits"
        ],
        "aiInvestmentMentioned": false,
        "priorGuidanceHit": null,
        "managementTone": "confident",
        "overallSentiment": "bullish",
        "summary": "Meta delivered strong Q1 performance with robust revenue and net income growth, driven by advertising resilience. The company continues to invest heavily in infrastructure and data centers while navigating complex regulatory challenges.",
        "keyQuotes": [
          "We extended the estimated useful lives of most servers and network assets to 5.5 years",
          "Our servers and network infrastructure investments remain a key strategic priority"
        ]
      },
      "quarter": "Q1 2025",
      "quarterInfo": {
        "calendarQuarter": 1,
        "calendarYear": 2025,
        "fiscalQuarter": 1,
        "fiscalYear": 2025,
        "quarter": "Q1 2025",
        "reportDate": "2025-03-31"
      },
      "analyzedSuccessfully": true
    },
    {
      "filing": {
        "accessionNumber": "0001326801-25-000017",
        "filingDate": "2025-01-30",
        "reportDate": "2024-12-31",
        "form": "10-K",
        "url": "https://www.sec.gov/Archives/edgar/data/1326801/000132680125000017/meta-20241231.htm"
      },
      "insights": {
        "guidanceTone": "cautious",
        "guidanceDirection": "maintained",
        "bookingsGrowth": null,
        "pricingPower": "moderate",
        "headcountTrend": "reducing",
        "revenue": 20290,
        "netIncome": -2395,
        "operatingCashFlow": null,
        "freeCashFlow": null,
        "daysalesOutstanding": null,
        "deferredRevenue": null,
        "marketShareMention": "facing significant competition across all aspects of business",
        "customerConcentration": null,
        "geographicBreakdown": null,
        "capexAmount": null,
        "capexGrowth": null,
        "partnerships": [],
        "supplyChainStatus": "tight",
        "regulatoryHeadwinds": [
          "Digital Services Act",
          "Digital Markets Act",
          "EU AI Act",
          "GDPR",
          "Privacy regulations"
        ],
        "aiInvestmentMentioned": true,
        "priorGuidanceHit": null,
        "managementTone": "defensive",
        "overallSentiment": "bearish",
        "summary": "Meta faces significant regulatory challenges, competitive pressures, and ongoing litigation risks. The company is investing heavily in AI while reducing headcount and managing complex global operational challenges.",
        "keyQuotes": [
          "We face significant competition in every aspect of our business",
          "Our financial results in any given quarter can be influenced by numerous factors, many of which we are unable to predict or are outside of our control"
        ]
      },
      "quarter": "Q4 2024",
      "quarterInfo": {
        "calendarQuarter": 4,
        "calendarYear": 2024,
        "fiscalQuarter": 4,
        "fiscalYear": 2024,
        "quarter": "Q4 2024",
        "reportDate": "2024-12-31"
      },
      "analyzedSuccessfully": true
    },
    {
      "filing": {
        "accessionNumber": "0001326801-24-000081",
        "filingDate": "2024-10-31",
        "reportDate": "2024-09-30",
        "form": "10-Q",
        "url": "https://www.sec.gov/Archives/edgar/data/1326801/000132680124000081/meta-20240930.htm"
      },
      "insights": {
        "guidanceTone": "positive",
        "guidanceDirection": "maintained",
        "bookingsGrowth": null,
        "pricingPower": "strong",
        "headcountTrend": "stable",
        "revenue": 40589,
        "netIncome": 15688,
        "operatingCashFlow": 63340,
        "freeCashFlow": null,
        "daysalesOutstanding": null,
        "deferredRevenue": 732,
        "marketShareMention": null,
        "customerConcentration": null,
        "geographicBreakdown": {
          "US_Canada": 38.5,
          "Europe": 22.7,
          "Asia_Pacific": 27.7,
          "Rest_of_World": 11.1
        },
        "capexAmount": 22831,
        "capexGrowth": null,
        "partnerships": [],
        "supplyChainStatus": "normal",
        "regulatoryHeadwinds": [],
        "aiInvestmentMentioned": false,
        "priorGuidanceHit": null,
        "managementTone": "confident",
        "overallSentiment": "bullish",
        "summary": "Meta delivered strong Q3 2024 financial performance with robust revenue growth and continued operational efficiency. The company maintained a confident stance, with solid revenue of $40.6B and net income of $15.7B, indicating strong market positioning and financial health.",
        "keyQuotes": []
      },
      "quarter": "Q3 2024",
      "quarterInfo": {
        "calendarQuarter": 3,
        "calendarYear": 2024,
        "fiscalQuarter": 3,
        "fiscalYear": 2024,
        "quarter": "Q3 2024",
        "reportDate": "2024-09-30"
      },
      "analyzedSuccessfully": true
    },
    {
      "filing": {
        "accessionNumber": "0001326801-24-000069",
        "filingDate": "2024-08-01",
        "reportDate": "2024-06-30",
        "form": "10-Q",
        "url": "https://www.sec.gov/Archives/edgar/data/1326801/000132680124000069/meta-20240630.htm"
      },
      "insights": {
        "guidanceTone": "positive",
        "guidanceDirection": "maintained",
        "bookingsGrowth": null,
        "pricingPower": "strong",
        "headcountTrend": "stable",
        "revenue": 39071,
        "netIncome": 13465,
        "operatingCashFlow": 38616,
        "freeCashFlow": null,
        "daysalesOutstanding": null,
        "deferredRevenue": 675,
        "marketShareMention": null,
        "customerConcentration": null,
        "geographicBreakdown": {
          "United States and Canada": 37.5,
          "Europe": 23.4,
          "Asia-Pacific": 28.1,
          "Rest of World": 11
        },
        "capexAmount": 14573,
        "capexGrowth": null,
        "partnerships": [],
        "supplyChainStatus": "normal",
        "regulatoryHeadwinds": [
          "Privacy investigations",
          "FTC consent order"
        ],
        "aiInvestmentMentioned": false,
        "priorGuidanceHit": null,
        "managementTone": "confident",
        "overallSentiment": "bullish",
        "summary": "Meta delivered strong Q2 2024 financial performance with robust revenue growth and continued efficiency. The company maintained solid profitability and geographic diversification while managing operational expenses effectively.",
        "keyQuotes": []
      },
      "quarter": "Q2 2024",
      "quarterInfo": {
        "calendarQuarter": 2,
        "calendarYear": 2024,
        "fiscalQuarter": 2,
        "fiscalYear": 2024,
        "quarter": "Q2 2024",
        "reportDate": "2024-06-30"
      },
      "analyzedSuccessfully": true
    },
    {
      "filing": {
        "accessionNumber": "0001326801-24-000049",
        "filingDate": "2024-04-25",
        "reportDate": "2024-03-31",
        "form": "10-Q",
        "url": "https://www.sec.gov/Archives/edgar/data/1326801/000132680124000049/meta-20240331.htm"
      },
      "insights": {
        "guidanceTone": "positive",
        "guidanceDirection": "raised",
        "bookingsGrowth": null,
        "pricingPower": "strong",
        "headcountTrend": "stable",
        "revenue": 36455,
        "netIncome": 12369,
        "operatingCashFlow": 19246,
        "freeCashFlow": null,
        "daysalesOutstanding": null,
        "deferredRevenue": 645,
        "marketShareMention": null,
        "customerConcentration": null,
        "geographicBreakdown": {
          "United States and Canada": 37.4,
          "Europe": 23,
          "Asia-Pacific": 28.3,
          "Rest of World": 11.3
        },
        "capexAmount": 6400,
        "capexGrowth": null,
        "partnerships": [],
        "supplyChainStatus": "normal",
        "regulatoryHeadwinds": [
          "FTC consent order modifications",
          "Privacy investigations"
        ],
        "aiInvestmentMentioned": false,
        "priorGuidanceHit": null,
        "managementTone": "confident",
        "overallSentiment": "bullish",
        "summary": "Meta delivered strong Q1 2024 results with revenue of $36.5B and net income of $12.4B, driven by continued ad platform strength and operational efficiency. The company remains focused on AI investments and managing regulatory challenges.",
        "keyQuotes": []
      },
      "quarter": "Q1 2024",
      "quarterInfo": {
        "calendarQuarter": 1,
        "calendarYear": 2024,
        "fiscalQuarter": 1,
        "fiscalYear": 2024,
        "quarter": "Q1 2024",
        "reportDate": "2024-03-31"
      },
      "analyzedSuccessfully": true
    }
  ],
  "totalFetched": 8,
  "successfulAnalyses": 7,
  "lastUpdated": "2025-11-13T21:53:26.624Z"
}