{
  "period": "Q4 2024",
  "generatedAt": "2026-01-21T23:57:16.036Z",
  "companies": [
    "AMC",
    "BIIB",
    "CEG",
    "CORZ",
    "DOCN",
    "HOOD",
    "IONQ",
    "REGN",
    "VST"
  ],
  "aggregateInsights": {
    "averageCapexGrowth": 247.6,
    "companiesRaisingGuidance": 2,
    "companiesLoweringGuidance": 1,
    "aiInvestmentCount": 6,
    "overallMarketSentiment": "neutral",
    "partnershipNetwork": [
      {
        "partner": "Eisai",
        "mentions": 1,
        "connectedCompanies": [
          "BIIB"
        ]
      },
      {
        "partner": "Sage",
        "mentions": 1,
        "connectedCompanies": [
          "BIIB"
        ]
      },
      {
        "partner": "Genentech",
        "mentions": 1,
        "connectedCompanies": [
          "BIIB"
        ]
      },
      {
        "partner": "Samsung",
        "mentions": 1,
        "connectedCompanies": [
          "BIIB"
        ]
      },
      {
        "partner": "Reata Pharmaceuticals",
        "mentions": 1,
        "connectedCompanies": [
          "BIIB"
        ]
      },
      {
        "partner": "Ionis Pharmaceuticals",
        "mentions": 1,
        "connectedCompanies": [
          "BIIB"
        ]
      },
      {
        "partner": "CoreWeave",
        "mentions": 1,
        "connectedCompanies": [
          "CORZ"
        ]
      },
      {
        "partner": "Hugging Face",
        "mentions": 1,
        "connectedCompanies": [
          "DOCN"
        ]
      },
      {
        "partner": "Morningstar",
        "mentions": 1,
        "connectedCompanies": [
          "HOOD"
        ]
      },
      {
        "partner": "Sanofi",
        "mentions": 1,
        "connectedCompanies": [
          "REGN"
        ]
      },
      {
        "partner": "Bayer",
        "mentions": 1,
        "connectedCompanies": [
          "REGN"
        ]
      },
      {
        "partner": "Roche",
        "mentions": 1,
        "connectedCompanies": [
          "REGN"
        ]
      },
      {
        "partner": "Sonoma Biotherapeutics",
        "mentions": 1,
        "connectedCompanies": [
          "REGN"
        ]
      },
      {
        "partner": "Alnylam Pharmaceuticals",
        "mentions": 1,
        "connectedCompanies": [
          "REGN"
        ]
      },
      {
        "partner": "Intellia Therapeutics",
        "mentions": 1,
        "connectedCompanies": [
          "REGN"
        ]
      }
    ],
    "supplyChainSentiment": {
      "tight": 5,
      "easing": 0,
      "normal": 3,
      "unknown": 1
    },
    "headcountTrends": {
      "expanding": 2,
      "stable": 4,
      "freezing": 0,
      "reducing": 3
    },
    "pricingPowerDistribution": {
      "strong": 2,
      "moderate": 5,
      "weak": 2,
      "unknown": 0
    }
  },
  "sectorAnalyses": [
    {
      "sector": "Consumer",
      "subCategory": "Other",
      "companies": [
        "AMC"
      ],
      "averageRevenueGrowth": 0,
      "averageCapexGrowth": 8.8,
      "guidanceSentiment": {
        "raised": 0,
        "maintained": 1,
        "lowered": 0,
        "notProvided": 0
      },
      "supplyChainStatus": {
        "tight": 0,
        "easing": 0,
        "normal": 1,
        "unknown": 0
      },
      "aiInvestmentPercentage": 100,
      "averageSentiment": 0,
      "topPartners": []
    },
    {
      "sector": "Healthcare",
      "subCategory": "Biotech",
      "companies": [
        "BIIB",
        "REGN"
      ],
      "averageRevenueGrowth": 0,
      "averageCapexGrowth": 0,
      "guidanceSentiment": {
        "raised": 0,
        "maintained": 1,
        "lowered": 0,
        "notProvided": 1
      },
      "supplyChainStatus": {
        "tight": 2,
        "easing": 0,
        "normal": 0,
        "unknown": 0
      },
      "aiInvestmentPercentage": 50,
      "averageSentiment": -0.5,
      "topPartners": [
        {
          "partner": "Samsung",
          "mentions": 2
        }
      ]
    },
    {
      "sector": "Energy",
      "subCategory": "Utilities",
      "companies": [
        "CEG",
        "VST"
      ],
      "averageRevenueGrowth": 0,
      "averageCapexGrowth": 0,
      "guidanceSentiment": {
        "raised": 2,
        "maintained": 0,
        "lowered": 0,
        "notProvided": 0
      },
      "supplyChainStatus": {
        "tight": 1,
        "easing": 0,
        "normal": 1,
        "unknown": 0
      },
      "aiInvestmentPercentage": 50,
      "averageSentiment": 1,
      "topPartners": []
    },
    {
      "sector": "Technology",
      "subCategory": "Data Centers",
      "companies": [
        "CORZ"
      ],
      "averageRevenueGrowth": 0,
      "averageCapexGrowth": 486.4,
      "guidanceSentiment": {
        "raised": 0,
        "maintained": 1,
        "lowered": 0,
        "notProvided": 0
      },
      "supplyChainStatus": {
        "tight": 1,
        "easing": 0,
        "normal": 0,
        "unknown": 0
      },
      "aiInvestmentPercentage": 100,
      "averageSentiment": 0,
      "topPartners": [
        {
          "partner": "CoreWeave",
          "mentions": 1
        }
      ]
    },
    {
      "sector": "Technology",
      "subCategory": "Cloud Infrastructure",
      "companies": [
        "DOCN"
      ],
      "averageRevenueGrowth": 0,
      "averageCapexGrowth": 0,
      "guidanceSentiment": {
        "raised": 0,
        "maintained": 1,
        "lowered": 0,
        "notProvided": 0
      },
      "supplyChainStatus": {
        "tight": 0,
        "easing": 0,
        "normal": 1,
        "unknown": 0
      },
      "aiInvestmentPercentage": 100,
      "averageSentiment": 0,
      "topPartners": [
        {
          "partner": "Hugging Face",
          "mentions": 1
        }
      ]
    },
    {
      "sector": "Technology",
      "subCategory": "FinTech",
      "companies": [
        "HOOD"
      ],
      "averageRevenueGrowth": 0,
      "averageCapexGrowth": 0,
      "guidanceSentiment": {
        "raised": 0,
        "maintained": 1,
        "lowered": 0,
        "notProvided": 0
      },
      "supplyChainStatus": {
        "tight": 0,
        "easing": 0,
        "normal": 0,
        "unknown": 1
      },
      "aiInvestmentPercentage": 100,
      "averageSentiment": -1,
      "topPartners": [
        {
          "partner": "Morningstar",
          "mentions": 1
        }
      ]
    },
    {
      "sector": "Technology",
      "subCategory": "Quantum Computing",
      "companies": [
        "IONQ"
      ],
      "averageRevenueGrowth": 0,
      "averageCapexGrowth": 0,
      "guidanceSentiment": {
        "raised": 0,
        "maintained": 0,
        "lowered": 1,
        "notProvided": 0
      },
      "supplyChainStatus": {
        "tight": 1,
        "easing": 0,
        "normal": 0,
        "unknown": 0
      },
      "aiInvestmentPercentage": 0,
      "averageSentiment": -1,
      "topPartners": []
    }
  ],
  "divergences": [
    {
      "theme": "Guidance Direction",
      "winners": [
        "CEG",
        "VST"
      ],
      "losers": [
        "IONQ"
      ],
      "details": "2 companies raised guidance vs 1 lowered"
    },
    {
      "theme": "Capital Expenditure",
      "winners": [
        "CORZ"
      ],
      "losers": [],
      "details": "1 companies increasing capex >20% vs 0 decreasing >10%"
    }
  ],
  "topThemes": [
    "AI Infrastructure Investment",
    "Supply Chain Constraints",
    "Cost Cutting Measures"
  ]
}